notifyemail/__init__.py
notifyemail/notify_backend.py
notifyemail/notify_frontend.py
notifyemail/tools.py
notifyemail-1.1.1.dist-info/LICENSE
notifyemail-1.1.1.dist-info/METADATA
notifyemail-1.1.1.dist-info/WHEEL
notifyemail-1.1.1.dist-info/top_level.txt
notifyemail-1.1.1.dist-info/RECORD
