Metadata-Version: 2.1
Name: notifyemail
Version: 1.1.1
Summary: python Email notification tool
Home-page: https://github.com/lsqqqq/notifyemail
Author: LvShangqing, ZhangTianyi, LeiYanli
Author-email: seblei@163.com
License: BSD License
Platform: all
Classifier: Intended Audience :: Developers
Classifier: Operating System :: OS Independent
Classifier: Natural Language :: Chinese (Simplified)
Classifier: Programming Language :: Python :: 3
Classifier: Programming Language :: Python :: 3.5
Classifier: Programming Language :: Python :: 3.6
Classifier: Programming Language :: Python :: 3.7
Classifier: Programming Language :: Python :: 3.8
Classifier: Programming Language :: Python :: 3.9
Classifier: Topic :: Software Development :: Libraries
License-File: LICENSE
